lord_of_the_rings_sdk/__init__.py
andrew_richards_sdk-0.0.1.dist-info/METADATA
andrew_richards_sdk-0.0.1.dist-info/WHEEL
andrew_richards_sdk-0.0.1.dist-info/top_level.txt
andrew_richards_sdk-0.0.1.dist-info/RECORD
