Metadata-Version: 2.1
Name: andrew-richards-sdk
Version: 0.0.1
Summary: Lord of the rings sdk in Python
Home-page: https://github.com/hope4lifeu/andrew-SDK
Author: Andrew Richard Asazobor
Author-email: asazobor.richards@gmail.com
Classifier: Programming Language :: Python :: 3
Classifier: License :: OSI Approved :: MIT License
Classifier: Operating System :: OS Independent
Requires-Python: >=3.6
